{
  "connection": "default",
  "collectionName": "post",
  "info": {
    "name": "post",
    "description": ""
  },
  "options": {
    "timestamps": true
  },
  "attributes": {
    "title_eng": {
      "default": "",
      "type": "string",
      "maxLength": 300,
      "required": true
    },
    "title": {
      "default": "",
      "type": "string",
      "maxLength": 300,
      "required": true
    },
    "title_az": {
      "default": "",
      "type": "string",
      "maxLength": 300,
      "required": true
    },
    "content_eng": {
      "default": "",
      "type": "text",
      "required": true
    },
    "description": {
      "default": "",
      "type": "string"
    },
    "content": {
      "default": "",
      "type": "text",
      "required": true
    },
    "content_az": {
      "default": "",
      "type": "text",
      "required": true
    },
    "cover": {
      "model": "file",
      "via": "related",
      "plugin": "upload",
      "required": true
    },
    "Избранное": {
      "default": false,
      "type": "boolean"
    },
    "recPosts": {
      "default": false,
      "type": "boolean"
    },
    "category": {
      "default": "Наши Беседы",
      "type": "enumeration",
      "required": true,
      "enum": [
        "Наши Беседы",
        "Фитнес",
        "Здоровье",
        "Питание",
        "Анонс"
      ]
    },
    "Count": {
      "default": 0,
      "type": "integer"
    }
  }
}